mcp_watchtower_campaign_config_agent/__init__.py
mcp_watchtower_campaign_config_agent/client.py
mcp_watchtower_campaign_config_agent/config.py
mcp_watchtower_campaign_config_agent/server.py
mcp_watchtower_campaign_config_agent/utils.py
mcp_watchtower_campaign_config_agent-0.1.1.dist-info/METADATA
mcp_watchtower_campaign_config_agent-0.1.1.dist-info/WHEEL
mcp_watchtower_campaign_config_agent-0.1.1.dist-info/entry_points.txt
mcp_watchtower_campaign_config_agent-0.1.1.dist-info/RECORD
