Metadata-Version: 2.4
Name: mcp-watchtower-campaign-config-agent
Version: 0.1.1
Summary: A Watchtower MCP agent for managing campaign-channel bindings. Features: - Get campaign info by ID/name - Bind campaigns to channels - List C-type campaigns  The agent operates as an MCP server component with JSON-based communication protocol.
Requires-Python: >=3.11
Requires-Dist: aiohttp>=3.8.0
Requires-Dist: httpx>=0.28.1
Requires-Dist: mcp>=1.5.0
Requires-Dist: pycryptodome>=3.19.0
Requires-Dist: pydantic>=2.0.0
Requires-Dist: python-dotenv>=1.0.1
